[
  {
    "id": "boar_intro",
    "displayName": "村外小冲突",
    "enemies": [
      {
        "id": "boar_intro_1",
        "displayName": "受惊野猪",
        "kind": "animal",
        "faction": "animal",
        "level": 1,
        "experience": 0,
        "unspentAttributePoints": 0,
        "stats": {
          "maxHealth": 18,
          "health": 18,
          "attack": 5,
          "defense": 2,
          "evasion": 2,
          "magic": 0,
          "maxActionPoints": 4,
          "actionPoints": 4
        },
        "classID": null,
        "skillIDs": ["boar_bite"],
        "equipment": {},
        "statuses": []
      },
      {
        "id": "poacher_intro_1",
        "displayName": "偷猎者",
        "kind": "humanEnemy",
        "faction": "hostile",
        "level": 1,
        "experience": 0,
        "unspentAttributePoints": 0,
        "stats": {
          "maxHealth": 16,
          "health": 16,
          "attack": 5,
          "defense": 1,
          "evasion": 4,
          "magic": 0,
          "maxActionPoints": 4,
          "actionPoints": 4
        },
        "classID": "archer",
        "skillIDs": ["poacher_shot"],
        "equipment": {},
        "statuses": []
      }
    ]
  },
  {
    "id": "road_bandit_ambush",
    "displayName": "断塔盗匪",
    "enemies": [
      {
        "id": "road_bandit_1",
        "displayName": "持刀盗匪",
        "kind": "humanEnemy",
        "faction": "hostile",
        "level": 2,
        "experience": 0,
        "unspentAttributePoints": 0,
        "stats": {
          "maxHealth": 22,
          "health": 22,
          "attack": 6,
          "defense": 3,
          "evasion": 3,
          "magic": 0,
          "maxActionPoints": 4,
          "actionPoints": 4
        },
        "classID": "warrior",
        "skillIDs": ["slash"],
        "equipment": {},
        "statuses": []
      },
      {
        "id": "road_bandit_2",
        "displayName": "断塔弓手",
        "kind": "humanEnemy",
        "faction": "hostile",
        "level": 2,
        "experience": 0,
        "unspentAttributePoints": 0,
        "stats": {
          "maxHealth": 18,
          "health": 18,
          "attack": 6,
          "defense": 2,
          "evasion": 5,
          "magic": 0,
          "maxActionPoints": 4,
          "actionPoints": 4
        },
        "classID": "archer",
        "skillIDs": ["poacher_shot"],
        "equipment": {},
        "statuses": []
      }
    ]
  },
  {
    "id": "ruins_element_raiders",
    "displayName": "废墟纵火者",
    "enemies": [
      {
        "id": "ruins_raider_1",
        "displayName": "纵火盗匪",
        "kind": "humanEnemy",
        "faction": "hostile",
        "level": 2,
        "experience": 0,
        "unspentAttributePoints": 0,
        "stats": {
          "maxHealth": 18,
          "health": 18,
          "attack": 3,
          "defense": 2,
          "evasion": 4,
          "magic": 6,
          "maxActionPoints": 4,
          "actionPoints": 4
        },
        "classID": "mage",
        "skillIDs": ["spark"],
        "equipment": {},
        "statuses": []
      },
      {
        "id": "ruins_raider_2",
        "displayName": "废墟刀手",
        "kind": "humanEnemy",
        "faction": "hostile",
        "level": 2,
        "experience": 0,
        "unspentAttributePoints": 0,
        "stats": {
          "maxHealth": 24,
          "health": 24,
          "attack": 7,
          "defense": 3,
          "evasion": 3,
          "magic": 0,
          "maxActionPoints": 4,
          "actionPoints": 4
        },
        "classID": "warrior",
        "skillIDs": ["slash"],
        "equipment": {},
        "statuses": []
      }
    ]
  },
  {
    "id": "cave_vermin",
    "displayName": "污染洞兽",
    "enemies": [
      {
        "id": "cave_vermin_1",
        "displayName": "污染洞兽",
        "kind": "monster",
        "faction": "monster",
        "level": 2,
        "experience": 0,
        "unspentAttributePoints": 0,
        "stats": {
          "maxHealth": 24,
          "health": 24,
          "attack": 7,
          "defense": 3,
          "evasion": 3,
          "magic": 1,
          "maxActionPoints": 4,
          "actionPoints": 4
        },
        "classID": null,
        "skillIDs": ["boar_bite"],
        "equipment": {},
        "statuses": []
      },
      {
        "id": "cave_vermin_2",
        "displayName": "小污染兽",
        "kind": "monster",
        "faction": "monster",
        "level": 1,
        "experience": 0,
        "unspentAttributePoints": 0,
        "stats": {
          "maxHealth": 16,
          "health": 16,
          "attack": 5,
          "defense": 2,
          "evasion": 4,
          "magic": 1,
          "maxActionPoints": 4,
          "actionPoints": 4
        },
        "classID": null,
        "skillIDs": ["boar_bite"],
        "equipment": {},
        "statuses": []
      }
    ]
  }
]
